{
    "protected": {
        "ver": "v1",
        "alg": "HS256",
        "iat": 1655065298.533412
    },
    "signature": "7f9fcfe08bef555a1448bd8df29a2fc1bbb7624b36189ba46a7c6f561344c461",
    "payload": {
        "device_name": "DI:C0:F3:08:33:96",
        "device_type": "Wio_Terminal",
        "interval_ms": 1,
        "sensors": [
            {
                "name": "temperature",
                "units": "Cel"
            }
        ],
        "values": [
            [
                25.73
            ],
            [
                26.65
            ],
            [
                26.18
            ],
            [
                26.34
            ],
            [
                24.82
            ],
            [
                24.79
            ],
            [
                24.61
            ],
            [
                25.47
            ],
            [
                26.58
            ],
            [
                26.41
            ],
            [
                24.11
            ],
            [
                23.93
            ],
            [
                23.77
            ],
            [
                23.8
            ],
            [
                23.9
            ],
            [
                24.08
            ],
            [
                23.93
            ],
            [
                24.36
            ],
            [
                23.95
            ],
            [
                23.94
            ],
            [
                23.75
            ],
            [
                23.91
            ],
            [
                23.52
            ],
            [
                23.75
            ],
            [
                23.98
            ],
            [
                24.05
            ],
            [
                23.89
            ],
            [
                24.01
            ],
            [
                24.4
            ],
            [
                24.86
            ],
            [
                24.27
            ],
            [
                24.34
            ],
            [
                27.18
            ],
            [
                26.07
            ],
            [
                26.72
            ],
            [
                26.52
            ],
            [
                25.13
            ],
            [
                24.52
            ],
            [
                25.09
            ],
            [
                25.92
            ],
            [
                28.39
            ],
            [
                27.08
            ],
            [
                24.43
            ],
            [
                24.13
            ],
            [
                23.87
            ],
            [
                23.66
            ],
            [
                23.88
            ],
            [
                23.98
            ],
            [
                24.07
            ],
            [
                24.04
            ],
            [
                24.05
            ],
            [
                24.13
            ],
            [
                23.98
            ],
            [
                23.7
            ],
            [
                23.95
            ],
            [
                23.77
            ],
            [
                23.64
            ],
            [
                23.52
            ],
            [
                24.16
            ],
            [
                24.4
            ],
            [
                25.05
            ],
            [
                24.07
            ],
            [
                23.51
            ],
            [
                23.99
            ],
            [
                27.36
            ],
            [
                27.7
            ],
            [
                26.71
            ],
            [
                26.41
            ],
            [
                24.65
            ],
            [
                25.52
            ],
            [
                26.3
            ],
            [
                27.27
            ],
            [
                28.89
            ],
            [
                29.15
            ],
            [
                25.78
            ],
            [
                24.5
            ],
            [
                23.86
            ],
            [
                23.98
            ],
            [
                24.15
            ],
            [
                24.33
            ],
            [
                24.1
            ],
            [
                24.33
            ],
            [
                23.97
            ],
            [
                23.92
            ],
            [
                23.69
            ],
            [
                23.91
            ],
            [
                23.74
            ],
            [
                23.77
            ],
            [
                23.49
            ],
            [
                23.82
            ],
            [
                23.99
            ],
            [
                24.09
            ],
            [
                23.82
            ],
            [
                23.81
            ],
            [
                23.51
            ],
            [
                23.82
            ],
            [
                27.67
            ],
            [
                26.95
            ],
            [
                27.21
            ],
            [
                26.22
            ],
            [
                26.09
            ],
            [
                26.48
            ],
            [
                28.05
            ],
            [
                28.1
            ],
            [
                28.98
            ],
            [
                29.06
            ],
            [
                27.35
            ],
            [
                25.3
            ],
            [
                24.15
            ],
            [
                24.04
            ],
            [
                24.29
            ],
            [
                24.48
            ],
            [
                24.48
            ],
            [
                24.08
            ],
            [
                24.09
            ],
            [
                23.88
            ],
            [
                24.07
            ],
            [
                23.86
            ],
            [
                23.69
            ],
            [
                23.78
            ],
            [
                23.86
            ],
            [
                23.5
            ],
            [
                24.0
            ],
            [
                23.83
            ],
            [
                24.03
            ],
            [
                23.57
            ],
            [
                23.54
            ],
            [
                23.76
            ],
            [
                27.18
            ],
            [
                27.58
            ],
            [
                26.19
            ],
            [
                26.04
            ],
            [
                28.09
            ],
            [
                29.11
            ],
            [
                29.71
            ],
            [
                29.76
            ],
            [
                28.82
            ],
            [
                28.94
            ],
            [
                28.6
            ],
            [
                26.89
            ],
            [
                23.85
            ],
            [
                24.19
            ],
            [
                24.96
            ],
            [
                25.22
            ],
            [
                24.71
            ],
            [
                24.35
            ],
            [
                23.86
            ],
            [
                24.02
            ],
            [
                23.76
            ],
            [
                23.95
            ],
            [
                23.67
            ],
            [
                23.78
            ],
            [
                23.54
            ],
            [
                23.86
            ],
            [
                23.79
            ],
            [
                23.97
            ],
            [
                23.77
            ],
            [
                24.15
            ],
            [
                23.67
            ],
            [
                23.46
            ],
            [
                27.92
            ],
            [
                27.1
            ],
            [
                26.06
            ],
            [
                25.82
            ],
            [
                28.44
            ],
            [
                29.35
            ],
            [
                29.08
            ],
            [
                28.53
            ],
            [
                28.17
            ],
            [
                27.13
            ],
            [
                27.51
            ],
            [
                26.35
            ],
            [
                24.23
            ],
            [
                24.22
            ],
            [
                25.5
            ],
            [
                25.57
            ],
            [
                25.14
            ],
            [
                24.45
            ],
            [
                24.12
            ],
            [
                23.78
            ],
            [
                23.89
            ],
            [
                23.66
            ],
            [
                23.71
            ],
            [
                23.63
            ],
            [
                23.78
            ],
            [
                23.73
            ],
            [
                23.87
            ],
            [
                23.78
            ],
            [
                23.93
            ],
            [
                23.63
            ],
            [
                23.88
            ],
            [
                23.81
            ],
            [
                27.24
            ],
            [
                27.09
            ],
            [
                25.58
            ],
            [
                25.55
            ],
            [
                28.39
            ],
            [
                29.42
            ],
            [
                29.24
            ],
            [
                28.88
            ],
            [
                26.97
            ],
            [
                25.26
            ],
            [
                23.58
            ],
            [
                24.17
            ],
            [
                24.25
            ],
            [
                24.63
            ],
            [
                26.59
            ],
            [
                26.82
            ],
            [
                25.16
            ],
            [
                24.58
            ],
            [
                24.05
            ],
            [
                24.43
            ],
            [
                23.74
            ],
            [
                23.9
            ],
            [
                23.93
            ],
            [
                23.88
            ],
            [
                23.8
            ],
            [
                24.14
            ],
            [
                24.09
            ],
            [
                24.28
            ],
            [
                23.91
            ],
            [
                24.05
            ],
            [
                23.76
            ],
            [
                23.7
            ],
            [
                27.93
            ],
            [
                26.72
            ],
            [
                25.07
            ],
            [
                25.04
            ],
            [
                28.43
            ],
            [
                29.3
            ],
            [
                30.0
            ],
            [
                29.74
            ],
            [
                26.75
            ],
            [
                24.94
            ],
            [
                23.63
            ],
            [
                23.62
            ],
            [
                24.14
            ],
            [
                24.71
            ],
            [
                27.02
            ],
            [
                27.27
            ],
            [
                25.67
            ],
            [
                24.81
            ],
            [
                24.43
            ],
            [
                24.66
            ],
            [
                24.34
            ],
            [
                24.02
            ],
            [
                24.0
            ],
            [
                23.82
            ],
            [
                24.01
            ],
            [
                24.04
            ],
            [
                24.27
            ],
            [
                24.24
            ],
            [
                24.41
            ],
            [
                24.25
            ],
            [
                23.56
            ],
            [
                23.59
            ],
            [
                27.53
            ],
            [
                26.84
            ],
            [
                23.87
            ],
            [
                23.75
            ],
            [
                25.83
            ],
            [
                27.38
            ],
            [
                30.39
            ],
            [
                30.31
            ],
            [
                26.51
            ],
            [
                24.74
            ],
            [
                23.98
            ],
            [
                24.36
            ],
            [
                24.44
            ],
            [
                25.1
            ],
            [
                27.13
            ],
            [
                27.71
            ],
            [
                28.28
            ],
            [
                28.53
            ],
            [
                30.78
            ],
            [
                30.0
            ],
            [
                25.21
            ],
            [
                24.76
            ],
            [
                24.05
            ],
            [
                24.03
            ],
            [
                24.05
            ],
            [
                24.3
            ],
            [
                24.53
            ],
            [
                24.48
            ],
            [
                24.27
            ],
            [
                24.39
            ],
            [
                23.66
            ],
            [
                23.93
            ],
            [
                28.0
            ],
            [
                26.92
            ],
            [
                24.38
            ],
            [
                23.87
            ],
            [
                24.74
            ],
            [
                25.12
            ],
            [
                29.36
            ],
            [
                29.8
            ],
            [
                26.66
            ],
            [
                24.66
            ],
            [
                24.2
            ],
            [
                24.49
            ],
            [
                24.95
            ],
            [
                25.5
            ],
            [
                27.62
            ],
            [
                28.3
            ],
            [
                34.49
            ],
            [
                39.11
            ],
            [
                42.79
            ],
            [
                36.51
            ],
            [
                26.04
            ],
            [
                24.82
            ],
            [
                24.11
            ],
            [
                24.2
            ],
            [
                24.46
            ],
            [
                24.33
            ],
            [
                24.47
            ],
            [
                24.32
            ],
            [
                24.58
            ],
            [
                24.01
            ],
            [
                24.11
            ],
            [
                24.05
            ],
            [
                28.99
            ],
            [
                28.89
            ],
            [
                24.64
            ],
            [
                24.08
            ],
            [
                23.04
            ],
            [
                23.25
            ],
            [
                24.8
            ],
            [
                26.56
            ],
            [
                25.54
            ],
            [
                24.64
            ],
            [
                24.14
            ],
            [
                24.45
            ],
            [
                24.9
            ],
            [
                26.57
            ],
            [
                28.5
            ],
            [
                29.39
            ],
            [
                35.98
            ],
            [
                43.01
            ],
            [
                46.89
            ],
            [
                37.52
            ],
            [
                25.13
            ],
            [
                24.58
            ],
            [
                24.14
            ],
            [
                24.19
            ],
            [
                23.99
            ],
            [
                24.4
            ],
            [
                24.59
            ],
            [
                24.93
            ],
            [
                24.61
            ],
            [
                25.03
            ],
            [
                24.82
            ],
            [
                24.38
            ],
            [
                29.65
            ],
            [
                28.44
            ],
            [
                25.09
            ],
            [
                23.49
            ],
            [
                23.4
            ],
            [
                22.93
            ],
            [
                24.27
            ],
            [
                24.92
            ],
            [
                24.94
            ],
            [
                24.26
            ],
            [
                24.19
            ],
            [
                24.31
            ],
            [
                25.48
            ],
            [
                26.05
            ],
            [
                29.22
            ],
            [
                29.41
            ],
            [
                31.53
            ],
            [
                32.72
            ],
            [
                35.02
            ],
            [
                31.08
            ],
            [
                24.94
            ],
            [
                24.3
            ],
            [
                24.36
            ],
            [
                24.46
            ],
            [
                24.75
            ],
            [
                24.43
            ],
            [
                24.67
            ],
            [
                24.62
            ],
            [
                24.83
            ],
            [
                24.95
            ],
            [
                25.05
            ],
            [
                24.61
            ],
            [
                29.23
            ],
            [
                29.09
            ],
            [
                25.34
            ],
            [
                24.52
            ],
            [
                24.13
            ],
            [
                24.25
            ],
            [
                24.29
            ],
            [
                24.5
            ],
            [
                24.87
            ],
            [
                25.08
            ],
            [
                24.6
            ],
            [
                25.08
            ],
            [
                25.42
            ],
            [
                26.24
            ],
            [
                28.96
            ],
            [
                29.91
            ],
            [
                29.85
            ],
            [
                29.97
            ],
            [
                28.68
            ],
            [
                27.49
            ],
            [
                24.73
            ],
            [
                24.27
            ],
            [
                24.41
            ],
            [
                24.85
            ],
            [
                24.95
            ],
            [
                25.07
            ],
            [
                24.85
            ],
            [
                24.8
            ],
            [
                24.75
            ],
            [
                24.79
            ],
            [
                24.95
            ],
            [
                24.53
            ],
            [
                29.06
            ],
            [
                28.2
            ],
            [
                25.58
            ],
            [
                24.89
            ],
            [
                24.78
            ],
            [
                24.54
            ],
            [
                24.78
            ],
            [
                24.74
            ],
            [
                25.31
            ],
            [
                24.88
            ],
            [
                24.9
            ],
            [
                25.12
            ],
            [
                25.73
            ],
            [
                25.94
            ],
            [
                28.17
            ],
            [
                28.65
            ],
            [
                29.26
            ],
            [
                29.16
            ],
            [
                27.93
            ],
            [
                27.09
            ],
            [
                24.91
            ],
            [
                24.17
            ],
            [
                24.68
            ],
            [
                24.89
            ],
            [
                25.35
            ],
            [
                25.23
            ],
            [
                25.04
            ],
            [
                25.05
            ],
            [
                25.07
            ],
            [
                24.81
            ],
            [
                24.86
            ],
            [
                24.75
            ],
            [
                28.27
            ],
            [
                28.99
            ],
            [
                26.53
            ],
            [
                25.58
            ],
            [
                24.97
            ],
            [
                25.12
            ],
            [
                25.11
            ],
            [
                25.22
            ],
            [
                25.45
            ],
            [
                25.57
            ],
            [
                25.14
            ],
            [
                25.4
            ],
            [
                25.54
            ],
            [
                25.88
            ],
            [
                26.3
            ],
            [
                26.76
            ],
            [
                26.67
            ],
            [
                27.01
            ],
            [
                26.24
            ],
            [
                25.93
            ],
            [
                24.74
            ],
            [
                24.46
            ],
            [
                24.87
            ],
            [
                25.16
            ],
            [
                25.08
            ],
            [
                25.35
            ],
            [
                25.26
            ],
            [
                25.63
            ],
            [
                25.21
            ],
            [
                25.43
            ],
            [
                24.93
            ],
            [
                25.04
            ],
            [
                28.34
            ],
            [
                28.34
            ],
            [
                26.65
            ],
            [
                25.56
            ],
            [
                25.12
            ],
            [
                24.95
            ],
            [
                25.38
            ],
            [
                25.48
            ],
            [
                25.85
            ],
            [
                25.56
            ],
            [
                25.46
            ],
            [
                25.41
            ],
            [
                25.82
            ],
            [
                25.58
            ],
            [
                26.36
            ],
            [
                26.19
            ],
            [
                26.33
            ],
            [
                26.23
            ],
            [
                25.86
            ],
            [
                25.67
            ],
            [
                25.15
            ],
            [
                24.94
            ],
            [
                25.24
            ],
            [
                25.5
            ],
            [
                25.41
            ],
            [
                25.39
            ],
            [
                25.87
            ],
            [
                25.6
            ],
            [
                25.31
            ],
            [
                25.34
            ],
            [
                25.34
            ],
            [
                25.28
            ],
            [
                26.35
            ],
            [
                26.76
            ],
            [
                25.38
            ],
            [
                25.45
            ],
            [
                24.82
            ],
            [
                25.51
            ],
            [
                25.28
            ],
            [
                25.52
            ],
            [
                25.63
            ],
            [
                25.95
            ],
            [
                25.9
            ],
            [
                25.94
            ],
            [
                25.76
            ],
            [
                25.99
            ],
            [
                26.11
            ],
            [
                26.19
            ],
            [
                26.01
            ],
            [
                26.34
            ],
            [
                25.99
            ],
            [
                26.06
            ],
            [
                25.56
            ],
            [
                25.81
            ],
            [
                25.65
            ],
            [
                25.75
            ],
            [
                25.46
            ],
            [
                25.77
            ],
            [
                25.6
            ],
            [
                26.06
            ],
            [
                25.51
            ],
            [
                25.92
            ],
            [
                25.9
            ],
            [
                25.92
            ],
            [
                25.72
            ],
            [
                25.24
            ],
            [
                25.4
            ],
            [
                24.98
            ],
            [
                25.24
            ],
            [
                25.19
            ],
            [
                25.31
            ],
            [
                25.39
            ],
            [
                25.85
            ],
            [
                25.92
            ],
            [
                25.93
            ],
            [
                25.93
            ],
            [
                26.12
            ],
            [
                25.92
            ],
            [
                26.12
            ],
            [
                26.24
            ],
            [
                26.29
            ],
            [
                26.1
            ],
            [
                26.23
            ],
            [
                25.98
            ],
            [
                25.97
            ],
            [
                25.87
            ],
            [
                25.9
            ],
            [
                25.88
            ],
            [
                25.93
            ],
            [
                25.79
            ],
            [
                26.03
            ],
            [
                25.87
            ],
            [
                25.94
            ],
            [
                25.54
            ],
            [
                25.56
            ],
            [
                25.82
            ],
            [
                24.74
            ],
            [
                25.14
            ],
            [
                25.15
            ],
            [
                25.2
            ],
            [
                24.56
            ],
            [
                24.96
            ],
            [
                25.08
            ],
            [
                25.68
            ],
            [
                25.82
            ],
            [
                25.85
            ],
            [
                25.95
            ],
            [
                25.98
            ],
            [
                25.88
            ],
            [
                26.34
            ],
            [
                26.41
            ],
            [
                26.45
            ],
            [
                26.39
            ],
            [
                26.52
            ],
            [
                26.67
            ],
            [
                26.43
            ],
            [
                25.99
            ],
            [
                26.33
            ],
            [
                26.04
            ],
            [
                26.15
            ],
            [
                25.75
            ],
            [
                26.01
            ],
            [
                25.72
            ],
            [
                25.76
            ],
            [
                25.71
            ],
            [
                25.95
            ],
            [
                25.7
            ],
            [
                25.62
            ],
            [
                25.4
            ],
            [
                24.66
            ],
            [
                24.79
            ],
            [
                24.75
            ],
            [
                25.0
            ],
            [
                25.06
            ],
            [
                25.48
            ],
            [
                25.34
            ],
            [
                25.64
            ],
            [
                25.6
            ],
            [
                26.04
            ],
            [
                25.96
            ],
            [
                26.18
            ],
            [
                26.09
            ],
            [
                26.38
            ],
            [
                26.59
            ],
            [
                26.56
            ],
            [
                26.42
            ],
            [
                26.52
            ],
            [
                26.47
            ],
            [
                26.29
            ],
            [
                25.99
            ],
            [
                26.03
            ],
            [
                26.3
            ],
            [
                25.97
            ],
            [
                25.79
            ],
            [
                25.72
            ],
            [
                25.89
            ],
            [
                25.68
            ],
            [
                25.51
            ],
            [
                25.89
            ],
            [
                25.75
            ],
            [
                24.98
            ],
            [
                24.61
            ],
            [
                24.72
            ],
            [
                25.22
            ],
            [
                24.87
            ],
            [
                25.05
            ],
            [
                25.2
            ],
            [
                25.35
            ],
            [
                25.44
            ],
            [
                25.63
            ],
            [
                25.81
            ],
            [
                25.81
            ],
            [
                25.65
            ],
            [
                26.01
            ],
            [
                25.99
            ],
            [
                26.34
            ],
            [
                26.16
            ],
            [
                26.45
            ],
            [
                27.64
            ],
            [
                28.96
            ],
            [
                28.64
            ],
            [
                27.69
            ],
            [
                26.07
            ],
            [
                25.96
            ],
            [
                25.67
            ],
            [
                25.88
            ],
            [
                25.56
            ],
            [
                25.93
            ],
            [
                25.41
            ],
            [
                25.74
            ],
            [
                25.52
            ],
            [
                25.68
            ],
            [
                25.29
            ],
            [
                24.86
            ],
            [
                24.91
            ],
            [
                25.04
            ],
            [
                25.36
            ],
            [
                24.78
            ],
            [
                25.21
            ],
            [
                25.34
            ],
            [
                25.42
            ],
            [
                25.52
            ],
            [
                25.61
            ],
            [
                25.62
            ],
            [
                25.83
            ],
            [
                25.69
            ],
            [
                26.16
            ],
            [
                26.14
            ],
            [
                26.36
            ],
            [
                26.44
            ],
            [
                29.71
            ],
            [
                31.5
            ],
            [
                31.71
            ],
            [
                29.53
            ],
            [
                26.26
            ],
            [
                26.41
            ],
            [
                25.99
            ],
            [
                25.6
            ],
            [
                25.62
            ],
            [
                25.43
            ],
            [
                25.71
            ],
            [
                25.92
            ],
            [
                25.76
            ],
            [
                25.78
            ],
            [
                24.61
            ],
            [
                24.96
            ],
            [
                24.73
            ],
            [
                24.94
            ],
            [
                24.89
            ],
            [
                25.24
            ],
            [
                25.08
            ],
            [
                25.57
            ],
            [
                25.44
            ],
            [
                25.44
            ],
            [
                25.49
            ],
            [
                25.6
            ],
            [
                25.27
            ],
            [
                25.71
            ],
            [
                25.71
            ],
            [
                25.99
            ],
            [
                26.14
            ],
            [
                26.61
            ],
            [
                29.58
            ],
            [
                30.67
            ],
            [
                30.45
            ],
            [
                29.37
            ],
            [
                27.03
            ],
            [
                26.93
            ],
            [
                26.0
            ],
            [
                26.02
            ],
            [
                25.56
            ],
            [
                25.89
            ],
            [
                25.2
            ],
            [
                25.76
            ],
            [
                25.48
            ],
            [
                25.99
            ],
            [
                25.07
            ],
            [
                24.69
            ],
            [
                24.76
            ],
            [
                24.74
            ],
            [
                25.24
            ],
            [
                24.8
            ],
            [
                25.2
            ],
            [
                25.27
            ],
            [
                25.28
            ],
            [
                25.23
            ],
            [
                25.42
            ],
            [
                25.47
            ],
            [
                25.71
            ],
            [
                25.42
            ],
            [
                25.65
            ],
            [
                25.76
            ],
            [
                26.37
            ],
            [
                26.4
            ],
            [
                28.14
            ],
            [
                28.42
            ],
            [
                28.46
            ],
            [
                27.78
            ],
            [
                26.91
            ],
            [
                26.65
            ],
            [
                26.22
            ],
            [
                25.96
            ],
            [
                25.64
            ],
            [
                25.83
            ],
            [
                25.63
            ],
            [
                25.43
            ],
            [
                25.72
            ],
            [
                25.39
            ]
        ]
    }
}